digquant/__init__.py
digquant/__main__.py
digquant/type.py
digquant/util/__init__.py
digquant/util/compression.py
digquant/util/dependency.py
digquant/util/path.py
digquant-0.3.3.dist-info/METADATA
digquant-0.3.3.dist-info/WHEEL
digquant-0.3.3.dist-info/entry_points.txt
digquant-0.3.3.dist-info/top_level.txt
digquant-0.3.3.dist-info/RECORD
