Metadata-Version: 2.4
Name: digquant
Version: 0.3.3
Summary: DigQuant
License-Expression: MIT
Project-URL: repository, https://github.com/digquant/digquant
Project-URL: issues, https://github.com/digquant/digquant/issues
Classifier: Operating System :: OS Independent
Classifier: Programming Language :: Python :: 3
Classifier: Topic :: Utilities
Requires-Python: >=3.9
Requires-Dist: click>=8.1.8
Requires-Dist: packaging>=25.0
Requires-Dist: pipdeptree>=2.28.0
Requires-Dist: requests>=2.32.5
Requires-Dist: tqdm>=4.67.1
Provides-Extra: data
Requires-Dist: pandas>=2.3.3; extra == "data"
Provides-Extra: par
Requires-Dist: joblib>=1.5.2; extra == "par"
Provides-Extra: ppt
Requires-Dist: python-pptx>=1.0.2; extra == "ppt"
Provides-Extra: web
Requires-Dist: flask>=3.1.2; extra == "web"
Requires-Dist: peewee>=3.18.3; extra == "web"
Provides-Extra: zstd
Requires-Dist: zstandard>=0.25.0; extra == "zstd"
